{
  "generated_at": "2025-08-16T13:20:21.354354",
  "source": "LEO_Phase1_System",
  "satellites": [
    {
      "norad_id": 44772,
      "name": "STARLINK-44772",
      "elevation_deg": 16.21,
      "azimuth_deg": 180.0,
      "distance_km": 7000.0,
      "line1": "1 44713U 19074A   25227.50000000  .00001234  00000-0  12345-3 0  9990",
      "line2": "2 44713  53.0000 123.4567 0001234  12.3456 347.6543 15.05000000123456",
      "ecef_x_km": null,
      "ecef_y_km": null,
      "ecef_z_km": null,
      "constellation": "STARLINK",
      "leo_visibility_analysis": {
        "total_visible_time_minutes": 31.5,
        "max_elevation_deg": 16.21,
        "visible_passes_count": 2,
        "avg_pass_duration_minutes": 15.75,
        "signal_strength_estimate_dbm": -66.2,
        "best_elevation_time": "2025-08-16T13:05:31.110522+00:00"
      },
      "leo_total_score": 72.03,
      "leo_visible_time_minutes": 31.5
    },
    {
      "norad_id": 44736,
      "name": "STARLINK-44736",
      "elevation_deg": 15.86,
      "azimuth_deg": 180.0,
      "distance_km": 7000.0,
      "line1": "1 44713U 19074A   25227.50000000  .00001234  00000-0  12345-3 0  9990",
      "line2": "2 44713  53.0000 123.4567 0001234  12.3456 347.6543 15.05000000123456",
      "ecef_x_km": null,
      "ecef_y_km": null,
      "ecef_z_km": null,
      "constellation": "STARLINK",
      "leo_visibility_analysis": {
        "total_visible_time_minutes": 25.5,
        "max_elevation_deg": 15.86,
        "visible_passes_count": 1,
        "avg_pass_duration_minutes": 25.5,
        "signal_strength_estimate_dbm": -66.8,
        "best_elevation_time": "2025-08-16T13:55:01.110522+00:00"
      },
      "leo_total_score": 67.98,
      "leo_visible_time_minutes": 25.5
    },
    {
      "norad_id": 44719,
      "name": "STARLINK-44719",
      "elevation_deg": 17.01,
      "azimuth_deg": 180.0,
      "distance_km": 7000.0,
      "line1": "1 44713U 19074A   25227.50000000  .00001234  00000-0  12345-3 0  9990",
      "line2": "2 44713  53.0000 123.4567 0001234  12.3456 347.6543 15.05000000123456",
      "ecef_x_km": null,
      "ecef_y_km": null,
      "ecef_z_km": null,
      "constellation": "STARLINK",
      "leo_visibility_analysis": {
        "total_visible_time_minutes": 24.5,
        "max_elevation_deg": 17.01,
        "visible_passes_count": 1,
        "avg_pass_duration_minutes": 24.5,
        "signal_strength_estimate_dbm": -65.54,
        "best_elevation_time": "2025-08-16T13:56:31.110522+00:00"
      },
      "leo_total_score": 67.5,
      "leo_visible_time_minutes": 24.5
    },
    {
      "norad_id": 44762,
      "name": "STARLINK-44762",
      "elevation_deg": 15.47,
      "azimuth_deg": 180.0,
      "distance_km": 7000.0,
      "line1": "1 44713U 19074A   25227.50000000  .00001234  00000-0  12345-3 0  9990",
      "line2": "2 44713  53.0000 123.4567 0001234  12.3456 347.6543 15.05000000123456",
      "ecef_x_km": null,
      "ecef_y_km": null,
      "ecef_z_km": null,
      "constellation": "STARLINK",
      "leo_visibility_analysis": {
        "total_visible_time_minutes": 24.5,
        "max_elevation_deg": 15.47,
        "visible_passes_count": 1,
        "avg_pass_duration_minutes": 24.5,
        "signal_strength_estimate_dbm": -66.77,
        "best_elevation_time": "2025-08-16T13:47:31.110522+00:00"
      },
      "leo_total_score": 67.24,
      "leo_visible_time_minutes": 24.5
    },
    {
      "norad_id": 44758,
      "name": "STARLINK-44758",
      "elevation_deg": 15.65,
      "azimuth_deg": 180.0,
      "distance_km": 7000.0,
      "line1": "1 44713U 19074A   25227.50000000  .00001234  00000-0  12345-3 0  9990",
      "line2": "2 44713  53.0000 123.4567 0001234  12.3456 347.6543 15.05000000123456",
      "ecef_x_km": null,
      "ecef_y_km": null,
      "ecef_z_km": null,
      "constellation": "STARLINK",
      "leo_visibility_analysis": {
        "total_visible_time_minutes": 25.5,
        "max_elevation_deg": 15.65,
        "visible_passes_count": 1,
        "avg_pass_duration_minutes": 25.5,
        "signal_strength_estimate_dbm": -66.83,
        "best_elevation_time": "2025-08-16T13:37:01.110522+00:00"
      },
      "leo_total_score": 67.94,
      "leo_visible_time_minutes": 25.5
    },
    {
      "norad_id": 44725,
      "name": "STARLINK-44725",
      "elevation_deg": 16.78,
      "azimuth_deg": 180.0,
      "distance_km": 7000.0,
      "line1": "1 44713U 19074A   25227.50000000  .00001234  00000-0  12345-3 0  9990",
      "line2": "2 44713  53.0000 123.4567 0001234  12.3456 347.6543 15.05000000123456",
      "ecef_x_km": null,
      "ecef_y_km": null,
      "ecef_z_km": null,
      "constellation": "STARLINK",
      "leo_visibility_analysis": {
        "total_visible_time_minutes": 28.0,
        "max_elevation_deg": 16.78,
        "visible_passes_count": 2,
        "avg_pass_duration_minutes": 14.0,
        "signal_strength_estimate_dbm": -66.38,
        "best_elevation_time": "2025-08-16T13:23:01.110522+00:00"
      },
      "leo_total_score": 69.8,
      "leo_visible_time_minutes": 28.0
    },
    {
      "norad_id": 44941,
      "name": "STARLINK-44941",
      "elevation_deg": 72.55,
      "azimuth_deg": 180.0,
      "distance_km": 7000.0,
      "line1": "1 44713U 19074A   25227.50000000  .00001234  00000-0  12345-3 0  9990",
      "line2": "2 44713  53.0000 123.4567 0001234  12.3456 347.6543 15.05000000123456",
      "ecef_x_km": null,
      "ecef_y_km": null,
      "ecef_z_km": null,
      "constellation": "STARLINK",
      "leo_visibility_analysis": {
        "total_visible_time_minutes": 33.0,
        "max_elevation_deg": 72.55,
        "visible_passes_count": 2,
        "avg_pass_duration_minutes": 16.5,
        "signal_strength_estimate_dbm": -56.86,
        "best_elevation_time": "2025-08-16T14:45:01.110522+00:00"
      },
      "leo_total_score": 82.43,
      "leo_visible_time_minutes": 33.0
    },
    {
      "norad_id": 44761,
      "name": "STARLINK-44761",
      "elevation_deg": 15.5,
      "azimuth_deg": 180.0,
      "distance_km": 7000.0,
      "line1": "1 44713U 19074A   25227.50000000  .00001234  00000-0  12345-3 0  9990",
      "line2": "2 44713  53.0000 123.4567 0001234  12.3456 347.6543 15.05000000123456",
      "ecef_x_km": null,
      "ecef_y_km": null,
      "ecef_z_km": null,
      "constellation": "STARLINK",
      "leo_visibility_analysis": {
        "total_visible_time_minutes": 25.0,
        "max_elevation_deg": 15.5,
        "visible_passes_count": 1,
        "avg_pass_duration_minutes": 25.0,
        "signal_strength_estimate_dbm": -66.85,
        "best_elevation_time": "2025-08-16T14:16:31.110522+00:00"
      },
      "leo_total_score": 67.58,
      "leo_visible_time_minutes": 25.0
    },
    {
      "norad_id": 44927,
      "name": "STARLINK-44927",
      "elevation_deg": 61.77,
      "azimuth_deg": 180.0,
      "distance_km": 7000.0,
      "line1": "1 44713U 19074A   25227.50000000  .00001234  00000-0  12345-3 0  9990",
      "line2": "2 44713  53.0000 123.4567 0001234  12.3456 347.6543 15.05000000123456",
      "ecef_x_km": null,
      "ecef_y_km": null,
      "ecef_z_km": null,
      "constellation": "STARLINK",
      "leo_visibility_analysis": {
        "total_visible_time_minutes": 29.0,
        "max_elevation_deg": 61.77,
        "visible_passes_count": 1,
        "avg_pass_duration_minutes": 29.0,
        "signal_strength_estimate_dbm": -56.26,
        "best_elevation_time": "2025-08-16T13:59:31.110522+00:00"
      },
      "leo_total_score": 77.96,
      "leo_visible_time_minutes": 29.0
    },
    {
      "norad_id": 44968,
      "name": "STARLINK-44968",
      "elevation_deg": 80.88,
      "azimuth_deg": 180.0,
      "distance_km": 7000.0,
      "line1": "1 44713U 19074A   25227.50000000  .00001234  00000-0  12345-3 0  9990",
      "line2": "2 44713  53.0000 123.4567 0001234  12.3456 347.6543 15.05000000123456",
      "ecef_x_km": null,
      "ecef_y_km": null,
      "ecef_z_km": null,
      "constellation": "STARLINK",
      "leo_visibility_analysis": {
        "total_visible_time_minutes": 29.0,
        "max_elevation_deg": 80.88,
        "visible_passes_count": 1,
        "avg_pass_duration_minutes": 29.0,
        "signal_strength_estimate_dbm": -55.86,
        "best_elevation_time": "2025-08-16T13:46:01.110522+00:00"
      },
      "leo_total_score": 81.15,
      "leo_visible_time_minutes": 29.0
    },
    {
      "norad_id": 44735,
      "name": "STARLINK-44735",
      "elevation_deg": 15.62,
      "azimuth_deg": 180.0,
      "distance_km": 7000.0,
      "line1": "1 44713U 19074A   25227.50000000  .00001234  00000-0  12345-3 0  9990",
      "line2": "2 44713  53.0000 123.4567 0001234  12.3456 347.6543 15.05000000123456",
      "ecef_x_km": null,
      "ecef_y_km": null,
      "ecef_z_km": null,
      "constellation": "STARLINK",
      "leo_visibility_analysis": {
        "total_visible_time_minutes": 24.5,
        "max_elevation_deg": 15.62,
        "visible_passes_count": 1,
        "avg_pass_duration_minutes": 24.5,
        "signal_strength_estimate_dbm": -66.6,
        "best_elevation_time": "2025-08-16T14:13:31.110522+00:00"
      },
      "leo_total_score": 67.27,
      "leo_visible_time_minutes": 24.5
    },
    {
      "norad_id": 44744,
      "name": "STARLINK-44744",
      "elevation_deg": 17.82,
      "azimuth_deg": 180.0,
      "distance_km": 7000.0,
      "line1": "1 44713U 19074A   25227.50000000  .00001234  00000-0  12345-3 0  9990",
      "line2": "2 44713  53.0000 123.4567 0001234  12.3456 347.6543 15.05000000123456",
      "ecef_x_km": null,
      "ecef_y_km": null,
      "ecef_z_km": null,
      "constellation": "STARLINK",
      "leo_visibility_analysis": {
        "total_visible_time_minutes": 27.0,
        "max_elevation_deg": 17.82,
        "visible_passes_count": 1,
        "avg_pass_duration_minutes": 27.0,
        "signal_strength_estimate_dbm": -65.63,
        "best_elevation_time": "2025-08-16T13:39:01.110522+00:00"
      },
      "leo_total_score": 69.3,
      "leo_visible_time_minutes": 27.0
    },
    {
      "norad_id": 45054,
      "name": "STARLINK-45054",
      "elevation_deg": 70.23,
      "azimuth_deg": 180.0,
      "distance_km": 7000.0,
      "line1": "1 44713U 19074A   25227.50000000  .00001234  00000-0  12345-3 0  9990",
      "line2": "2 44713  53.0000 123.4567 0001234  12.3456 347.6543 15.05000000123456",
      "ecef_x_km": null,
      "ecef_y_km": null,
      "ecef_z_km": null,
      "constellation": "STARLINK",
      "leo_visibility_analysis": {
        "total_visible_time_minutes": 33.0,
        "max_elevation_deg": 70.23,
        "visible_passes_count": 2,
        "avg_pass_duration_minutes": 16.5,
        "signal_strength_estimate_dbm": -58.15,
        "best_elevation_time": "2025-08-16T13:08:31.110522+00:00"
      },
      "leo_total_score": 82.04,
      "leo_visible_time_minutes": 33.0
    },
    {
      "norad_id": 44747,
      "name": "STARLINK-44747",
      "elevation_deg": 17.25,
      "azimuth_deg": 180.0,
      "distance_km": 7000.0,
      "line1": "1 44713U 19074A   25227.50000000  .00001234  00000-0  12345-3 0  9990",
      "line2": "2 44713  53.0000 123.4567 0001234  12.3456 347.6543 15.05000000123456",
      "ecef_x_km": null,
      "ecef_y_km": null,
      "ecef_z_km": null,
      "constellation": "STARLINK",
      "leo_visibility_analysis": {
        "total_visible_time_minutes": 32.5,
        "max_elevation_deg": 17.25,
        "visible_passes_count": 2,
        "avg_pass_duration_minutes": 16.25,
        "signal_strength_estimate_dbm": -66.19,
        "best_elevation_time": "2025-08-16T14:30:31.110522+00:00"
      },
      "leo_total_score": 72.88,
      "leo_visible_time_minutes": 32.5
    },
    {
      "norad_id": 44751,
      "name": "STARLINK-44751",
      "elevation_deg": 17.66,
      "azimuth_deg": 180.0,
      "distance_km": 7000.0,
      "line1": "1 44713U 19074A   25227.50000000  .00001234  00000-0  12345-3 0  9990",
      "line2": "2 44713  53.0000 123.4567 0001234  12.3456 347.6543 15.05000000123456",
      "ecef_x_km": null,
      "ecef_y_km": null,
      "ecef_z_km": null,
      "constellation": "STARLINK",
      "leo_visibility_analysis": {
        "total_visible_time_minutes": 27.0,
        "max_elevation_deg": 17.66,
        "visible_passes_count": 1,
        "avg_pass_duration_minutes": 27.0,
        "signal_strength_estimate_dbm": -65.7,
        "best_elevation_time": "2025-08-16T13:48:01.110522+00:00"
      },
      "leo_total_score": 69.28,
      "leo_visible_time_minutes": 27.0
    },
    {
      "norad_id": 44771,
      "name": "STARLINK-44771",
      "elevation_deg": 18.38,
      "azimuth_deg": 180.0,
      "distance_km": 7000.0,
      "line1": "1 44713U 19074A   25227.50000000  .00001234  00000-0  12345-3 0  9990",
      "line2": "2 44713  53.0000 123.4567 0001234  12.3456 347.6543 15.05000000123456",
      "ecef_x_km": null,
      "ecef_y_km": null,
      "ecef_z_km": null,
      "constellation": "STARLINK",
      "leo_visibility_analysis": {
        "total_visible_time_minutes": 31.5,
        "max_elevation_deg": 18.38,
        "visible_passes_count": 2,
        "avg_pass_duration_minutes": 15.75,
        "signal_strength_estimate_dbm": -65.53,
        "best_elevation_time": "2025-08-16T13:16:31.110522+00:00"
      },
      "leo_total_score": 72.4,
      "leo_visible_time_minutes": 31.5
    },
    {
      "norad_id": 44934,
      "name": "STARLINK-44934",
      "elevation_deg": 27.69,
      "azimuth_deg": 180.0,
      "distance_km": 7000.0,
      "line1": "1 44713U 19074A   25227.50000000  .00001234  00000-0  12345-3 0  9990",
      "line2": "2 44713  53.0000 123.4567 0001234  12.3456 347.6543 15.05000000123456",
      "ecef_x_km": null,
      "ecef_y_km": null,
      "ecef_z_km": null,
      "constellation": "STARLINK",
      "leo_visibility_analysis": {
        "total_visible_time_minutes": 26.5,
        "max_elevation_deg": 27.69,
        "visible_passes_count": 1,
        "avg_pass_duration_minutes": 26.5,
        "signal_strength_estimate_dbm": -60.58,
        "best_elevation_time": "2025-08-16T14:00:31.110522+00:00"
      },
      "leo_total_score": 70.62,
      "leo_visible_time_minutes": 26.5
    },
    {
      "norad_id": 44753,
      "name": "STARLINK-44753",
      "elevation_deg": 16.08,
      "azimuth_deg": 180.0,
      "distance_km": 7000.0,
      "line1": "1 44713U 19074A   25227.50000000  .00001234  00000-0  12345-3 0  9990",
      "line2": "2 44713  53.0000 123.4567 0001234  12.3456 347.6543 15.05000000123456",
      "ecef_x_km": null,
      "ecef_y_km": null,
      "ecef_z_km": null,
      "constellation": "STARLINK",
      "leo_visibility_analysis": {
        "total_visible_time_minutes": 26.5,
        "max_elevation_deg": 16.08,
        "visible_passes_count": 1,
        "avg_pass_duration_minutes": 26.5,
        "signal_strength_estimate_dbm": -66.82,
        "best_elevation_time": "2025-08-16T14:22:31.110522+00:00"
      },
      "leo_total_score": 68.68,
      "leo_visible_time_minutes": 26.5
    },
    {
      "norad_id": 45060,
      "name": "STARLINK-45060",
      "elevation_deg": 37.81,
      "azimuth_deg": 180.0,
      "distance_km": 7000.0,
      "line1": "1 44713U 19074A   25227.50000000  .00001234  00000-0  12345-3 0  9990",
      "line2": "2 44713  53.0000 123.4567 0001234  12.3456 347.6543 15.05000000123456",
      "ecef_x_km": null,
      "ecef_y_km": null,
      "ecef_z_km": null,
      "constellation": "STARLINK",
      "leo_visibility_analysis": {
        "total_visible_time_minutes": 29.0,
        "max_elevation_deg": 37.81,
        "visible_passes_count": 1,
        "avg_pass_duration_minutes": 29.0,
        "signal_strength_estimate_dbm": -58.36,
        "best_elevation_time": "2025-08-16T13:43:01.110522+00:00"
      },
      "leo_total_score": 73.97,
      "leo_visible_time_minutes": 29.0
    },
    {
      "norad_id": 44723,
      "name": "STARLINK-44723",
      "elevation_deg": 16.04,
      "azimuth_deg": 180.0,
      "distance_km": 7000.0,
      "line1": "1 44713U 19074A   25227.50000000  .00001234  00000-0  12345-3 0  9990",
      "line2": "2 44713  53.0000 123.4567 0001234  12.3456 347.6543 15.05000000123456",
      "ecef_x_km": null,
      "ecef_y_km": null,
      "ecef_z_km": null,
      "constellation": "STARLINK",
      "leo_visibility_analysis": {
        "total_visible_time_minutes": 26.5,
        "max_elevation_deg": 16.04,
        "visible_passes_count": 1,
        "avg_pass_duration_minutes": 26.5,
        "signal_strength_estimate_dbm": -66.83,
        "best_elevation_time": "2025-08-16T14:13:31.110522+00:00"
      },
      "leo_total_score": 68.67,
      "leo_visible_time_minutes": 26.5
    },
    {
      "norad_id": 44759,
      "name": "STARLINK-44759",
      "elevation_deg": 16.02,
      "azimuth_deg": 180.0,
      "distance_km": 7000.0,
      "line1": "1 44713U 19074A   25227.50000000  .00001234  00000-0  12345-3 0  9990",
      "line2": "2 44713  53.0000 123.4567 0001234  12.3456 347.6543 15.05000000123456",
      "ecef_x_km": null,
      "ecef_y_km": null,
      "ecef_z_km": null,
      "constellation": "STARLINK",
      "leo_visibility_analysis": {
        "total_visible_time_minutes": 25.0,
        "max_elevation_deg": 16.02,
        "visible_passes_count": 1,
        "avg_pass_duration_minutes": 25.0,
        "signal_strength_estimate_dbm": -66.52,
        "best_elevation_time": "2025-08-16T13:32:01.110522+00:00"
      },
      "leo_total_score": 67.67,
      "leo_visible_time_minutes": 25.0
    },
    {
      "norad_id": 44748,
      "name": "STARLINK-44748",
      "elevation_deg": 18.12,
      "azimuth_deg": 180.0,
      "distance_km": 7000.0,
      "line1": "1 44713U 19074A   25227.50000000  .00001234  00000-0  12345-3 0  9990",
      "line2": "2 44713  53.0000 123.4567 0001234  12.3456 347.6543 15.05000000123456",
      "ecef_x_km": null,
      "ecef_y_km": null,
      "ecef_z_km": null,
      "constellation": "STARLINK",
      "leo_visibility_analysis": {
        "total_visible_time_minutes": 27.0,
        "max_elevation_deg": 18.12,
        "visible_passes_count": 1,
        "avg_pass_duration_minutes": 27.0,
        "signal_strength_estimate_dbm": -65.48,
        "best_elevation_time": "2025-08-16T13:27:01.110522+00:00"
      },
      "leo_total_score": 69.35,
      "leo_visible_time_minutes": 27.0
    },
    {
      "norad_id": 45048,
      "name": "STARLINK-45048",
      "elevation_deg": 29.75,
      "azimuth_deg": 180.0,
      "distance_km": 7000.0,
      "line1": "1 44713U 19074A   25227.50000000  .00001234  00000-0  12345-3 0  9990",
      "line2": "2 44713  53.0000 123.4567 0001234  12.3456 347.6543 15.05000000123456",
      "ecef_x_km": null,
      "ecef_y_km": null,
      "ecef_z_km": null,
      "constellation": "STARLINK",
      "leo_visibility_analysis": {
        "total_visible_time_minutes": 33.5,
        "max_elevation_deg": 29.75,
        "visible_passes_count": 2,
        "avg_pass_duration_minutes": 16.75,
        "signal_strength_estimate_dbm": -61.47,
        "best_elevation_time": "2025-08-16T13:26:01.110522+00:00"
      },
      "leo_total_score": 75.62,
      "leo_visible_time_minutes": 33.5
    },
    {
      "norad_id": 44721,
      "name": "STARLINK-44721",
      "elevation_deg": 17.59,
      "azimuth_deg": 180.0,
      "distance_km": 7000.0,
      "line1": "1 44713U 19074A   25227.50000000  .00001234  00000-0  12345-3 0  9990",
      "line2": "2 44713  53.0000 123.4567 0001234  12.3456 347.6543 15.05000000123456",
      "ecef_x_km": null,
      "ecef_y_km": null,
      "ecef_z_km": null,
      "constellation": "STARLINK",
      "leo_visibility_analysis": {
        "total_visible_time_minutes": 34.5,
        "max_elevation_deg": 17.59,
        "visible_passes_count": 2,
        "avg_pass_duration_minutes": 17.25,
        "signal_strength_estimate_dbm": -65.45,
        "best_elevation_time": "2025-08-16T14:44:01.110522+00:00"
      },
      "leo_total_score": 74.26,
      "leo_visible_time_minutes": 34.5
    },
    {
      "norad_id": 45047,
      "name": "STARLINK-45047",
      "elevation_deg": 36.72,
      "azimuth_deg": 180.0,
      "distance_km": 7000.0,
      "line1": "1 44713U 19074A   25227.50000000  .00001234  00000-0  12345-3 0  9990",
      "line2": "2 44713  53.0000 123.4567 0001234  12.3456 347.6543 15.05000000123456",
      "ecef_x_km": null,
      "ecef_y_km": null,
      "ecef_z_km": null,
      "constellation": "STARLINK",
      "leo_visibility_analysis": {
        "total_visible_time_minutes": 29.0,
        "max_elevation_deg": 36.72,
        "visible_passes_count": 1,
        "avg_pass_duration_minutes": 29.0,
        "signal_strength_estimate_dbm": -58.85,
        "best_elevation_time": "2025-08-16T13:48:01.110522+00:00"
      },
      "leo_total_score": 73.79,
      "leo_visible_time_minutes": 29.0
    },
    {
      "norad_id": 44973,
      "name": "STARLINK-44973",
      "elevation_deg": 16.0,
      "azimuth_deg": 180.0,
      "distance_km": 7000.0,
      "line1": "1 44713U 19074A   25227.50000000  .00001234  00000-0  12345-3 0  9990",
      "line2": "2 44713  53.0000 123.4567 0001234  12.3456 347.6543 15.05000000123456",
      "ecef_x_km": null,
      "ecef_y_km": null,
      "ecef_z_km": null,
      "constellation": "STARLINK",
      "leo_visibility_analysis": {
        "total_visible_time_minutes": 34.5,
        "max_elevation_deg": 16.0,
        "visible_passes_count": 2,
        "avg_pass_duration_minutes": 17.25,
        "signal_strength_estimate_dbm": -66.45,
        "best_elevation_time": "2025-08-16T13:17:01.110522+00:00"
      },
      "leo_total_score": 74.0,
      "leo_visible_time_minutes": 34.5
    },
    {
      "norad_id": 44726,
      "name": "STARLINK-44726",
      "elevation_deg": 16.56,
      "azimuth_deg": 180.0,
      "distance_km": 7000.0,
      "line1": "1 44713U 19074A   25227.50000000  .00001234  00000-0  12345-3 0  9990",
      "line2": "2 44713  53.0000 123.4567 0001234  12.3456 347.6543 15.05000000123456",
      "ecef_x_km": null,
      "ecef_y_km": null,
      "ecef_z_km": null,
      "constellation": "STARLINK",
      "leo_visibility_analysis": {
        "total_visible_time_minutes": 33.0,
        "max_elevation_deg": 16.56,
        "visible_passes_count": 2,
        "avg_pass_duration_minutes": 16.5,
        "signal_strength_estimate_dbm": -65.75,
        "best_elevation_time": "2025-08-16T14:45:01.110522+00:00"
      },
      "leo_total_score": 73.09,
      "leo_visible_time_minutes": 33.0
    },
    {
      "norad_id": 45057,
      "name": "STARLINK-45057",
      "elevation_deg": 46.17,
      "azimuth_deg": 180.0,
      "distance_km": 7000.0,
      "line1": "1 44713U 19074A   25227.50000000  .00001234  00000-0  12345-3 0  9990",
      "line2": "2 44713  53.0000 123.4567 0001234  12.3456 347.6543 15.05000000123456",
      "ecef_x_km": null,
      "ecef_y_km": null,
      "ecef_z_km": null,
      "constellation": "STARLINK",
      "leo_visibility_analysis": {
        "total_visible_time_minutes": 33.5,
        "max_elevation_deg": 46.17,
        "visible_passes_count": 2,
        "avg_pass_duration_minutes": 16.75,
        "signal_strength_estimate_dbm": -58.72,
        "best_elevation_time": "2025-08-16T13:29:01.110522+00:00"
      },
      "leo_total_score": 78.36,
      "leo_visible_time_minutes": 33.5
    },
    {
      "norad_id": 44718,
      "name": "STARLINK-44718",
      "elevation_deg": 16.16,
      "azimuth_deg": 180.0,
      "distance_km": 7000.0,
      "line1": "1 44713U 19074A   25227.50000000  .00001234  00000-0  12345-3 0  9990",
      "line2": "2 44713  53.0000 123.4567 0001234  12.3456 347.6543 15.05000000123456",
      "ecef_x_km": null,
      "ecef_y_km": null,
      "ecef_z_km": null,
      "constellation": "STARLINK",
      "leo_visibility_analysis": {
        "total_visible_time_minutes": 31.0,
        "max_elevation_deg": 16.16,
        "visible_passes_count": 2,
        "avg_pass_duration_minutes": 15.5,
        "signal_strength_estimate_dbm": -66.71,
        "best_elevation_time": "2025-08-16T13:19:31.110522+00:00"
      },
      "leo_total_score": 71.69,
      "leo_visible_time_minutes": 31.0
    },
    {
      "norad_id": 44961,
      "name": "STARLINK-44961",
      "elevation_deg": 78.57,
      "azimuth_deg": 180.0,
      "distance_km": 7000.0,
      "line1": "1 44713U 19074A   25227.50000000  .00001234  00000-0  12345-3 0  9990",
      "line2": "2 44713  53.0000 123.4567 0001234  12.3456 347.6543 15.05000000123456",
      "ecef_x_km": null,
      "ecef_y_km": null,
      "ecef_z_km": null,
      "constellation": "STARLINK",
      "leo_visibility_analysis": {
        "total_visible_time_minutes": 29.0,
        "max_elevation_deg": 78.57,
        "visible_passes_count": 1,
        "avg_pass_duration_minutes": 29.0,
        "signal_strength_estimate_dbm": -55.67,
        "best_elevation_time": "2025-08-16T13:40:31.110522+00:00"
      },
      "leo_total_score": 80.76,
      "leo_visible_time_minutes": 29.0
    },
    {
      "norad_id": 44933,
      "name": "STARLINK-44933",
      "elevation_deg": 85.24,
      "azimuth_deg": 180.0,
      "distance_km": 7000.0,
      "line1": "1 44713U 19074A   25227.50000000  .00001234  00000-0  12345-3 0  9990",
      "line2": "2 44713  53.0000 123.4567 0001234  12.3456 347.6543 15.05000000123456",
      "ecef_x_km": null,
      "ecef_y_km": null,
      "ecef_z_km": null,
      "constellation": "STARLINK",
      "leo_visibility_analysis": {
        "total_visible_time_minutes": 28.0,
        "max_elevation_deg": 85.24,
        "visible_passes_count": 1,
        "avg_pass_duration_minutes": 28.0,
        "signal_strength_estimate_dbm": -55.76,
        "best_elevation_time": "2025-08-16T14:01:01.110522+00:00"
      },
      "leo_total_score": 81.21,
      "leo_visible_time_minutes": 28.0
    },
    {
      "norad_id": 44922,
      "name": "STARLINK-44922",
      "elevation_deg": 74.46,
      "azimuth_deg": 180.0,
      "distance_km": 7000.0,
      "line1": "1 44713U 19074A   25227.50000000  .00001234  00000-0  12345-3 0  9990",
      "line2": "2 44713  53.0000 123.4567 0001234  12.3456 347.6543 15.05000000123456",
      "ecef_x_km": null,
      "ecef_y_km": null,
      "ecef_z_km": null,
      "constellation": "STARLINK",
      "leo_visibility_analysis": {
        "total_visible_time_minutes": 27.0,
        "max_elevation_deg": 74.46,
        "visible_passes_count": 1,
        "avg_pass_duration_minutes": 27.0,
        "signal_strength_estimate_dbm": -55.74,
        "best_elevation_time": "2025-08-16T13:55:31.110522+00:00"
      },
      "leo_total_score": 78.74,
      "leo_visible_time_minutes": 27.0
    },
    {
      "norad_id": 44949,
      "name": "STARLINK-44949",
      "elevation_deg": 65.39,
      "azimuth_deg": 180.0,
      "distance_km": 7000.0,
      "line1": "1 44713U 19074A   25227.50000000  .00001234  00000-0  12345-3 0  9990",
      "line2": "2 44713  53.0000 123.4567 0001234  12.3456 347.6543 15.05000000123456",
      "ecef_x_km": null,
      "ecef_y_km": null,
      "ecef_z_km": null,
      "constellation": "STARLINK",
      "leo_visibility_analysis": {
        "total_visible_time_minutes": 29.0,
        "max_elevation_deg": 65.39,
        "visible_passes_count": 1,
        "avg_pass_duration_minutes": 29.0,
        "signal_strength_estimate_dbm": -56.08,
        "best_elevation_time": "2025-08-16T13:38:31.110522+00:00"
      },
      "leo_total_score": 78.56,
      "leo_visible_time_minutes": 29.0
    },
    {
      "norad_id": 44917,
      "name": "STARLINK-44917",
      "elevation_deg": 84.08,
      "azimuth_deg": 180.0,
      "distance_km": 7000.0,
      "line1": "1 44713U 19074A   25227.50000000  .00001234  00000-0  12345-3 0  9990",
      "line2": "2 44713  53.0000 123.4567 0001234  12.3456 347.6543 15.05000000123456",
      "ecef_x_km": null,
      "ecef_y_km": null,
      "ecef_z_km": null,
      "constellation": "STARLINK",
      "leo_visibility_analysis": {
        "total_visible_time_minutes": 27.0,
        "max_elevation_deg": 84.08,
        "visible_passes_count": 1,
        "avg_pass_duration_minutes": 27.0,
        "signal_strength_estimate_dbm": -55.81,
        "best_elevation_time": "2025-08-16T14:09:01.110522+00:00"
      },
      "leo_total_score": 80.35,
      "leo_visible_time_minutes": 27.0
    },
    {
      "norad_id": 44930,
      "name": "STARLINK-44930",
      "elevation_deg": 62.88,
      "azimuth_deg": 180.0,
      "distance_km": 7000.0,
      "line1": "1 44713U 19074A   25227.50000000  .00001234  00000-0  12345-3 0  9990",
      "line2": "2 44713  53.0000 123.4567 0001234  12.3456 347.6543 15.05000000123456",
      "ecef_x_km": null,
      "ecef_y_km": null,
      "ecef_z_km": null,
      "constellation": "STARLINK",
      "leo_visibility_analysis": {
        "total_visible_time_minutes": 28.5,
        "max_elevation_deg": 62.88,
        "visible_passes_count": 1,
        "avg_pass_duration_minutes": 28.5,
        "signal_strength_estimate_dbm": -56.07,
        "best_elevation_time": "2025-08-16T14:22:01.110522+00:00"
      },
      "leo_total_score": 77.81,
      "leo_visible_time_minutes": 28.5
    },
    {
      "norad_id": 44752,
      "name": "STARLINK-44752",
      "elevation_deg": 15.89,
      "azimuth_deg": 180.0,
      "distance_km": 7000.0,
      "line1": "1 44713U 19074A   25227.50000000  .00001234  00000-0  12345-3 0  9990",
      "line2": "2 44713  53.0000 123.4567 0001234  12.3456 347.6543 15.05000000123456",
      "ecef_x_km": null,
      "ecef_y_km": null,
      "ecef_z_km": null,
      "constellation": "STARLINK",
      "leo_visibility_analysis": {
        "total_visible_time_minutes": 26.0,
        "max_elevation_deg": 15.89,
        "visible_passes_count": 1,
        "avg_pass_duration_minutes": 26.0,
        "signal_strength_estimate_dbm": -66.83,
        "best_elevation_time": "2025-08-16T13:54:01.110522+00:00"
      },
      "leo_total_score": 68.31,
      "leo_visible_time_minutes": 26.0
    },
    {
      "norad_id": 44714,
      "name": "STARLINK-44714",
      "elevation_deg": 16.07,
      "azimuth_deg": 180.0,
      "distance_km": 7000.0,
      "line1": "1 44713U 19074A   25227.50000000  .00001234  00000-0  12345-3 0  9990",
      "line2": "2 44713  53.0000 123.4567 0001234  12.3456 347.6543 15.05000000123456",
      "ecef_x_km": null,
      "ecef_y_km": null,
      "ecef_z_km": null,
      "constellation": "STARLINK",
      "leo_visibility_analysis": {
        "total_visible_time_minutes": 26.0,
        "max_elevation_deg": 16.07,
        "visible_passes_count": 1,
        "avg_pass_duration_minutes": 26.0,
        "signal_strength_estimate_dbm": -66.82,
        "best_elevation_time": "2025-08-16T13:51:01.110522+00:00"
      },
      "leo_total_score": 68.35,
      "leo_visible_time_minutes": 26.0
    },
    {
      "norad_id": 45044,
      "name": "STARLINK-45044",
      "elevation_deg": 22.23,
      "azimuth_deg": 180.0,
      "distance_km": 7000.0,
      "line1": "1 44713U 19074A   25227.50000000  .00001234  00000-0  12345-3 0  9990",
      "line2": "2 44713  53.0000 123.4567 0001234  12.3456 347.6543 15.05000000123456",
      "ecef_x_km": null,
      "ecef_y_km": null,
      "ecef_z_km": null,
      "constellation": "STARLINK",
      "leo_visibility_analysis": {
        "total_visible_time_minutes": 27.5,
        "max_elevation_deg": 22.23,
        "visible_passes_count": 1,
        "avg_pass_duration_minutes": 27.5,
        "signal_strength_estimate_dbm": -63.22,
        "best_elevation_time": "2025-08-16T14:17:01.110522+00:00"
      },
      "leo_total_score": 70.37,
      "leo_visible_time_minutes": 27.5
    },
    {
      "norad_id": 44925,
      "name": "STARLINK-44925",
      "elevation_deg": 65.85,
      "azimuth_deg": 180.0,
      "distance_km": 7000.0,
      "line1": "1 44713U 19074A   25227.50000000  .00001234  00000-0  12345-3 0  9990",
      "line2": "2 44713  53.0000 123.4567 0001234  12.3456 347.6543 15.05000000123456",
      "ecef_x_km": null,
      "ecef_y_km": null,
      "ecef_z_km": null,
      "constellation": "STARLINK",
      "leo_visibility_analysis": {
        "total_visible_time_minutes": 28.0,
        "max_elevation_deg": 65.85,
        "visible_passes_count": 1,
        "avg_pass_duration_minutes": 28.0,
        "signal_strength_estimate_dbm": -56.0,
        "best_elevation_time": "2025-08-16T14:03:31.110522+00:00"
      },
      "leo_total_score": 77.98,
      "leo_visible_time_minutes": 28.0
    },
    {
      "norad_id": 44972,
      "name": "STARLINK-44972",
      "elevation_deg": 19.18,
      "azimuth_deg": 180.0,
      "distance_km": 7000.0,
      "line1": "1 44713U 19074A   25227.50000000  .00001234  00000-0  12345-3 0  9990",
      "line2": "2 44713  53.0000 123.4567 0001234  12.3456 347.6543 15.05000000123456",
      "ecef_x_km": null,
      "ecef_y_km": null,
      "ecef_z_km": null,
      "constellation": "STARLINK",
      "leo_visibility_analysis": {
        "total_visible_time_minutes": 26.5,
        "max_elevation_deg": 19.18,
        "visible_passes_count": 1,
        "avg_pass_duration_minutes": 26.5,
        "signal_strength_estimate_dbm": -64.54,
        "best_elevation_time": "2025-08-16T13:59:31.110522+00:00"
      },
      "leo_total_score": 69.2,
      "leo_visible_time_minutes": 26.5
    },
    {
      "norad_id": 44765,
      "name": "STARLINK-44765",
      "elevation_deg": 16.92,
      "azimuth_deg": 180.0,
      "distance_km": 7000.0,
      "line1": "1 44713U 19074A   25227.50000000  .00001234  00000-0  12345-3 0  9990",
      "line2": "2 44713  53.0000 123.4567 0001234  12.3456 347.6543 15.05000000123456",
      "ecef_x_km": null,
      "ecef_y_km": null,
      "ecef_z_km": null,
      "constellation": "STARLINK",
      "leo_visibility_analysis": {
        "total_visible_time_minutes": 31.5,
        "max_elevation_deg": 16.92,
        "visible_passes_count": 2,
        "avg_pass_duration_minutes": 15.75,
        "signal_strength_estimate_dbm": -66.16,
        "best_elevation_time": "2025-08-16T13:12:31.110522+00:00"
      },
      "leo_total_score": 72.15,
      "leo_visible_time_minutes": 31.5
    },
    {
      "norad_id": 44741,
      "name": "STARLINK-44741",
      "elevation_deg": 16.36,
      "azimuth_deg": 180.0,
      "distance_km": 7000.0,
      "line1": "1 44713U 19074A   25227.50000000  .00001234  00000-0  12345-3 0  9990",
      "line2": "2 44713  53.0000 123.4567 0001234  12.3456 347.6543 15.05000000123456",
      "ecef_x_km": null,
      "ecef_y_km": null,
      "ecef_z_km": null,
      "constellation": "STARLINK",
      "leo_visibility_analysis": {
        "total_visible_time_minutes": 27.0,
        "max_elevation_deg": 16.36,
        "visible_passes_count": 1,
        "avg_pass_duration_minutes": 27.0,
        "signal_strength_estimate_dbm": -66.63,
        "best_elevation_time": "2025-08-16T14:05:01.110522+00:00"
      },
      "leo_total_score": 69.06,
      "leo_visible_time_minutes": 27.0
    },
    {
      "norad_id": 44954,
      "name": "STARLINK-44954",
      "elevation_deg": 24.8,
      "azimuth_deg": 180.0,
      "distance_km": 7000.0,
      "line1": "1 44713U 19074A   25227.50000000  .00001234  00000-0  12345-3 0  9990",
      "line2": "2 44713  53.0000 123.4567 0001234  12.3456 347.6543 15.05000000123456",
      "ecef_x_km": null,
      "ecef_y_km": null,
      "ecef_z_km": null,
      "constellation": "STARLINK",
      "leo_visibility_analysis": {
        "total_visible_time_minutes": 32.0,
        "max_elevation_deg": 24.8,
        "visible_passes_count": 2,
        "avg_pass_duration_minutes": 16.0,
        "signal_strength_estimate_dbm": -62.67,
        "best_elevation_time": "2025-08-16T13:27:01.110522+00:00"
      },
      "leo_total_score": 73.8,
      "leo_visible_time_minutes": 32.0
    },
    {
      "norad_id": 44724,
      "name": "STARLINK-44724",
      "elevation_deg": 16.18,
      "azimuth_deg": 180.0,
      "distance_km": 7000.0,
      "line1": "1 44713U 19074A   25227.50000000  .00001234  00000-0  12345-3 0  9990",
      "line2": "2 44713  53.0000 123.4567 0001234  12.3456 347.6543 15.05000000123456",
      "ecef_x_km": null,
      "ecef_y_km": null,
      "ecef_z_km": null,
      "constellation": "STARLINK",
      "leo_visibility_analysis": {
        "total_visible_time_minutes": 31.0,
        "max_elevation_deg": 16.18,
        "visible_passes_count": 2,
        "avg_pass_duration_minutes": 15.5,
        "signal_strength_estimate_dbm": -66.48,
        "best_elevation_time": "2025-08-16T13:14:01.110522+00:00"
      },
      "leo_total_score": 71.7,
      "leo_visible_time_minutes": 31.0
    },
    {
      "norad_id": 44734,
      "name": "STARLINK-44734",
      "elevation_deg": 85.77,
      "azimuth_deg": 180.0,
      "distance_km": 7000.0,
      "line1": "1 44713U 19074A   25227.50000000  .00001234  00000-0  12345-3 0  9990",
      "line2": "2 44713  53.0000 123.4567 0001234  12.3456 347.6543 15.05000000123456",
      "ecef_x_km": null,
      "ecef_y_km": null,
      "ecef_z_km": null,
      "constellation": "STARLINK",
      "leo_visibility_analysis": {
        "total_visible_time_minutes": 27.5,
        "max_elevation_deg": 85.77,
        "visible_passes_count": 1,
        "avg_pass_duration_minutes": 27.5,
        "signal_strength_estimate_dbm": -55.8,
        "best_elevation_time": "2025-08-16T14:04:01.110522+00:00"
      },
      "leo_total_score": 80.96,
      "leo_visible_time_minutes": 27.5
    },
    {
      "norad_id": 44940,
      "name": "STARLINK-44940",
      "elevation_deg": 75.29,
      "azimuth_deg": 180.0,
      "distance_km": 7000.0,
      "line1": "1 44713U 19074A   25227.50000000  .00001234  00000-0  12345-3 0  9990",
      "line2": "2 44713  53.0000 123.4567 0001234  12.3456 347.6543 15.05000000123456",
      "ecef_x_km": null,
      "ecef_y_km": null,
      "ecef_z_km": null,
      "constellation": "STARLINK",
      "leo_visibility_analysis": {
        "total_visible_time_minutes": 35.0,
        "max_elevation_deg": 75.29,
        "visible_passes_count": 2,
        "avg_pass_duration_minutes": 17.5,
        "signal_strength_estimate_dbm": -56.35,
        "best_elevation_time": "2025-08-16T13:11:01.110522+00:00"
      },
      "leo_total_score": 84.22,
      "leo_visible_time_minutes": 35.0
    },
    {
      "norad_id": 44716,
      "name": "STARLINK-44716",
      "elevation_deg": 16.39,
      "azimuth_deg": 180.0,
      "distance_km": 7000.0,
      "line1": "1 44713U 19074A   25227.50000000  .00001234  00000-0  12345-3 0  9990",
      "line2": "2 44713  53.0000 123.4567 0001234  12.3456 347.6543 15.05000000123456",
      "ecef_x_km": null,
      "ecef_y_km": null,
      "ecef_z_km": null,
      "constellation": "STARLINK",
      "leo_visibility_analysis": {
        "total_visible_time_minutes": 25.5,
        "max_elevation_deg": 16.39,
        "visible_passes_count": 1,
        "avg_pass_duration_minutes": 25.5,
        "signal_strength_estimate_dbm": -66.19,
        "best_elevation_time": "2025-08-16T14:07:31.110522+00:00"
      },
      "leo_total_score": 68.06,
      "leo_visible_time_minutes": 25.5
    },
    {
      "norad_id": 44768,
      "name": "STARLINK-44768",
      "elevation_deg": 18.0,
      "azimuth_deg": 180.0,
      "distance_km": 7000.0,
      "line1": "1 44713U 19074A   25227.50000000  .00001234  00000-0  12345-3 0  9990",
      "line2": "2 44713  53.0000 123.4567 0001234  12.3456 347.6543 15.05000000123456",
      "ecef_x_km": null,
      "ecef_y_km": null,
      "ecef_z_km": null,
      "constellation": "STARLINK",
      "leo_visibility_analysis": {
        "total_visible_time_minutes": 27.0,
        "max_elevation_deg": 18.0,
        "visible_passes_count": 1,
        "avg_pass_duration_minutes": 27.0,
        "signal_strength_estimate_dbm": -65.5,
        "best_elevation_time": "2025-08-16T13:32:01.110522+00:00"
      },
      "leo_total_score": 69.33,
      "leo_visible_time_minutes": 27.0
    },
    {
      "norad_id": 44942,
      "name": "STARLINK-44942",
      "elevation_deg": 18.17,
      "azimuth_deg": 180.0,
      "distance_km": 7000.0,
      "line1": "1 44713U 19074A   25227.50000000  .00001234  00000-0  12345-3 0  9990",
      "line2": "2 44713  53.0000 123.4567 0001234  12.3456 347.6543 15.05000000123456",
      "ecef_x_km": null,
      "ecef_y_km": null,
      "ecef_z_km": null,
      "constellation": "STARLINK",
      "leo_visibility_analysis": {
        "total_visible_time_minutes": 25.5,
        "max_elevation_deg": 18.17,
        "visible_passes_count": 1,
        "avg_pass_duration_minutes": 25.5,
        "signal_strength_estimate_dbm": -64.95,
        "best_elevation_time": "2025-08-16T13:45:01.110522+00:00"
      },
      "leo_total_score": 68.36,
      "leo_visible_time_minutes": 25.5
    },
    {
      "norad_id": 44717,
      "name": "STARLINK-44717",
      "elevation_deg": 16.01,
      "azimuth_deg": 180.0,
      "distance_km": 7000.0,
      "line1": "1 44713U 19074A   25227.50000000  .00001234  00000-0  12345-3 0  9990",
      "line2": "2 44713  53.0000 123.4567 0001234  12.3456 347.6543 15.05000000123456",
      "ecef_x_km": null,
      "ecef_y_km": null,
      "ecef_z_km": null,
      "constellation": "STARLINK",
      "leo_visibility_analysis": {
        "total_visible_time_minutes": 25.5,
        "max_elevation_deg": 16.01,
        "visible_passes_count": 1,
        "avg_pass_duration_minutes": 25.5,
        "signal_strength_estimate_dbm": -66.55,
        "best_elevation_time": "2025-08-16T13:38:31.110522+00:00"
      },
      "leo_total_score": 68.0,
      "leo_visible_time_minutes": 25.5
    },
    {
      "norad_id": 45425,
      "name": "ONEWEB-45425",
      "elevation_deg": 51.81,
      "azimuth_deg": 180.0,
      "distance_km": 7000.0,
      "line1": "1 44713U 19074A   25227.50000000  .00001234  00000-0  12345-3 0  9990",
      "line2": "2 44713  87.9000 123.4567 0001234  12.3456 347.6543 13.20000000123456",
      "ecef_x_km": null,
      "ecef_y_km": null,
      "ecef_z_km": null,
      "constellation": "ONEWEB",
      "leo_visibility_analysis": {
        "total_visible_time_minutes": 26.5,
        "max_elevation_deg": 51.81,
        "visible_passes_count": 1,
        "avg_pass_duration_minutes": 26.5,
        "signal_strength_estimate_dbm": -57.64,
        "best_elevation_time": "2025-08-16T13:21:31.110522+00:00"
      },
      "leo_total_score": 74.63,
      "leo_visible_time_minutes": 26.5
    },
    {
      "norad_id": 45141,
      "name": "ONEWEB-45141",
      "elevation_deg": 53.89,
      "azimuth_deg": 180.0,
      "distance_km": 7000.0,
      "line1": "1 44713U 19074A   25227.50000000  .00001234  00000-0  12345-3 0  9990",
      "line2": "2 44713  87.9000 123.4567 0001234  12.3456 347.6543 13.20000000123456",
      "ecef_x_km": null,
      "ecef_y_km": null,
      "ecef_z_km": null,
      "constellation": "ONEWEB",
      "leo_visibility_analysis": {
        "total_visible_time_minutes": 35.5,
        "max_elevation_deg": 53.89,
        "visible_passes_count": 1,
        "avg_pass_duration_minutes": 35.5,
        "signal_strength_estimate_dbm": -59.51,
        "best_elevation_time": "2025-08-16T14:09:31.110522+00:00"
      },
      "leo_total_score": 80.98,
      "leo_visible_time_minutes": 35.5
    },
    {
      "norad_id": 45155,
      "name": "ONEWEB-45155",
      "elevation_deg": 44.4,
      "azimuth_deg": 180.0,
      "distance_km": 7000.0,
      "line1": "1 44713U 19074A   25227.50000000  .00001234  00000-0  12345-3 0  9990",
      "line2": "2 44713  87.9000 123.4567 0001234  12.3456 347.6543 13.20000000123456",
      "ecef_x_km": null,
      "ecef_y_km": null,
      "ecef_z_km": null,
      "constellation": "ONEWEB",
      "leo_visibility_analysis": {
        "total_visible_time_minutes": 31.0,
        "max_elevation_deg": 44.4,
        "visible_passes_count": 1,
        "avg_pass_duration_minutes": 31.0,
        "signal_strength_estimate_dbm": -61.38,
        "best_elevation_time": "2025-08-16T14:36:01.110522+00:00"
      },
      "leo_total_score": 76.4,
      "leo_visible_time_minutes": 31.0
    },
    {
      "norad_id": 45433,
      "name": "ONEWEB-45433",
      "elevation_deg": 51.57,
      "azimuth_deg": 180.0,
      "distance_km": 7000.0,
      "line1": "1 44713U 19074A   25227.50000000  .00001234  00000-0  12345-3 0  9990",
      "line2": "2 44713  87.9000 123.4567 0001234  12.3456 347.6543 13.20000000123456",
      "ecef_x_km": null,
      "ecef_y_km": null,
      "ecef_z_km": null,
      "constellation": "ONEWEB",
      "leo_visibility_analysis": {
        "total_visible_time_minutes": 29.0,
        "max_elevation_deg": 51.57,
        "visible_passes_count": 1,
        "avg_pass_duration_minutes": 29.0,
        "signal_strength_estimate_dbm": -58.22,
        "best_elevation_time": "2025-08-16T13:23:31.110522+00:00"
      },
      "leo_total_score": 76.26,
      "leo_visible_time_minutes": 29.0
    },
    {
      "norad_id": 45145,
      "name": "ONEWEB-45145",
      "elevation_deg": 43.71,
      "azimuth_deg": 180.0,
      "distance_km": 7000.0,
      "line1": "1 44713U 19074A   25227.50000000  .00001234  00000-0  12345-3 0  9990",
      "line2": "2 44713  87.9000 123.4567 0001234  12.3456 347.6543 13.20000000123456",
      "ecef_x_km": null,
      "ecef_y_km": null,
      "ecef_z_km": null,
      "constellation": "ONEWEB",
      "leo_visibility_analysis": {
        "total_visible_time_minutes": 26.0,
        "max_elevation_deg": 43.71,
        "visible_passes_count": 2,
        "avg_pass_duration_minutes": 13.0,
        "signal_strength_estimate_dbm": -61.07,
        "best_elevation_time": "2025-08-16T13:05:31.110522+00:00"
      },
      "leo_total_score": 72.95,
      "leo_visible_time_minutes": 26.0
    },
    {
      "norad_id": 45430,
      "name": "ONEWEB-45430",
      "elevation_deg": 46.9,
      "azimuth_deg": 180.0,
      "distance_km": 7000.0,
      "line1": "1 44713U 19074A   25227.50000000  .00001234  00000-0  12345-3 0  9990",
      "line2": "2 44713  87.9000 123.4567 0001234  12.3456 347.6543 13.20000000123456",
      "ecef_x_km": null,
      "ecef_y_km": null,
      "ecef_z_km": null,
      "constellation": "ONEWEB",
      "leo_visibility_analysis": {
        "total_visible_time_minutes": 35.0,
        "max_elevation_deg": 46.9,
        "visible_passes_count": 1,
        "avg_pass_duration_minutes": 35.0,
        "signal_strength_estimate_dbm": -60.65,
        "best_elevation_time": "2025-08-16T14:04:31.110522+00:00"
      },
      "leo_total_score": 79.48,
      "leo_visible_time_minutes": 35.0
    },
    {
      "norad_id": 45432,
      "name": "ONEWEB-45432",
      "elevation_deg": 41.84,
      "azimuth_deg": 180.0,
      "distance_km": 7000.0,
      "line1": "1 44713U 19074A   25227.50000000  .00001234  00000-0  12345-3 0  9990",
      "line2": "2 44713  87.9000 123.4567 0001234  12.3456 347.6543 13.20000000123456",
      "ecef_x_km": null,
      "ecef_y_km": null,
      "ecef_z_km": null,
      "constellation": "ONEWEB",
      "leo_visibility_analysis": {
        "total_visible_time_minutes": 34.5,
        "max_elevation_deg": 41.84,
        "visible_passes_count": 1,
        "avg_pass_duration_minutes": 34.5,
        "signal_strength_estimate_dbm": -61.67,
        "best_elevation_time": "2025-08-16T14:18:01.110522+00:00"
      },
      "leo_total_score": 78.31,
      "leo_visible_time_minutes": 34.5
    },
    {
      "norad_id": 45136,
      "name": "ONEWEB-45136",
      "elevation_deg": 55.29,
      "azimuth_deg": 180.0,
      "distance_km": 7000.0,
      "line1": "1 44713U 19074A   25227.50000000  .00001234  00000-0  12345-3 0  9990",
      "line2": "2 44713  87.9000 123.4567 0001234  12.3456 347.6543 13.20000000123456",
      "ecef_x_km": null,
      "ecef_y_km": null,
      "ecef_z_km": null,
      "constellation": "ONEWEB",
      "leo_visibility_analysis": {
        "total_visible_time_minutes": 35.5,
        "max_elevation_deg": 55.29,
        "visible_passes_count": 1,
        "avg_pass_duration_minutes": 35.5,
        "signal_strength_estimate_dbm": -59.2,
        "best_elevation_time": "2025-08-16T14:01:31.110522+00:00"
      },
      "leo_total_score": 81.21,
      "leo_visible_time_minutes": 35.5
    },
    {
      "norad_id": 45131,
      "name": "ONEWEB-45131",
      "elevation_deg": 69.88,
      "azimuth_deg": 180.0,
      "distance_km": 7000.0,
      "line1": "1 44713U 19074A   25227.50000000  .00001234  00000-0  12345-3 0  9990",
      "line2": "2 44713  87.9000 123.4567 0001234  12.3456 347.6543 13.20000000123456",
      "ecef_x_km": null,
      "ecef_y_km": null,
      "ecef_z_km": null,
      "constellation": "ONEWEB",
      "leo_visibility_analysis": {
        "total_visible_time_minutes": 26.0,
        "max_elevation_deg": 69.88,
        "visible_passes_count": 2,
        "avg_pass_duration_minutes": 13.0,
        "signal_strength_estimate_dbm": -59.29,
        "best_elevation_time": "2025-08-16T13:05:31.110522+00:00"
      },
      "leo_total_score": 77.31,
      "leo_visible_time_minutes": 26.0
    },
    {
      "norad_id": 45132,
      "name": "ONEWEB-45132",
      "elevation_deg": 54.25,
      "azimuth_deg": 180.0,
      "distance_km": 7000.0,
      "line1": "1 44713U 19074A   25227.50000000  .00001234  00000-0  12345-3 0  9990",
      "line2": "2 44713  87.9000 123.4567 0001234  12.3456 347.6543 13.20000000123456",
      "ecef_x_km": null,
      "ecef_y_km": null,
      "ecef_z_km": null,
      "constellation": "ONEWEB",
      "leo_visibility_analysis": {
        "total_visible_time_minutes": 35.5,
        "max_elevation_deg": 54.25,
        "visible_passes_count": 1,
        "avg_pass_duration_minutes": 35.5,
        "signal_strength_estimate_dbm": -59.38,
        "best_elevation_time": "2025-08-16T14:07:31.110522+00:00"
      },
      "leo_total_score": 81.04,
      "leo_visible_time_minutes": 35.5
    },
    {
      "norad_id": 44062,
      "name": "ONEWEB-44062",
      "elevation_deg": 48.93,
      "azimuth_deg": 180.0,
      "distance_km": 7000.0,
      "line1": "1 44713U 19074A   25227.50000000  .00001234  00000-0  12345-3 0  9990",
      "line2": "2 44713  87.9000 123.4567 0001234  12.3456 347.6543 13.20000000123456",
      "ecef_x_km": null,
      "ecef_y_km": null,
      "ecef_z_km": null,
      "constellation": "ONEWEB",
      "leo_visibility_analysis": {
        "total_visible_time_minutes": 35.0,
        "max_elevation_deg": 48.93,
        "visible_passes_count": 1,
        "avg_pass_duration_minutes": 35.0,
        "signal_strength_estimate_dbm": -60.16,
        "best_elevation_time": "2025-08-16T13:30:31.110522+00:00"
      },
      "leo_total_score": 79.82,
      "leo_visible_time_minutes": 35.0
    },
    {
      "norad_id": 45149,
      "name": "ONEWEB-45149",
      "elevation_deg": 61.75,
      "azimuth_deg": 180.0,
      "distance_km": 7000.0,
      "line1": "1 44713U 19074A   25227.50000000  .00001234  00000-0  12345-3 0  9990",
      "line2": "2 44713  87.9000 123.4567 0001234  12.3456 347.6543 13.20000000123456",
      "ecef_x_km": null,
      "ecef_y_km": null,
      "ecef_z_km": null,
      "constellation": "ONEWEB",
      "leo_visibility_analysis": {
        "total_visible_time_minutes": 36.0,
        "max_elevation_deg": 61.75,
        "visible_passes_count": 1,
        "avg_pass_duration_minutes": 36.0,
        "signal_strength_estimate_dbm": -58.45,
        "best_elevation_time": "2025-08-16T13:33:31.110522+00:00"
      },
      "leo_total_score": 82.62,
      "leo_visible_time_minutes": 36.0
    },
    {
      "norad_id": 45161,
      "name": "ONEWEB-45161",
      "elevation_deg": 59.35,
      "azimuth_deg": 180.0,
      "distance_km": 7000.0,
      "line1": "1 44713U 19074A   25227.50000000  .00001234  00000-0  12345-3 0  9990",
      "line2": "2 44713  87.9000 123.4567 0001234  12.3456 347.6543 13.20000000123456",
      "ecef_x_km": null,
      "ecef_y_km": null,
      "ecef_z_km": null,
      "constellation": "ONEWEB",
      "leo_visibility_analysis": {
        "total_visible_time_minutes": 36.0,
        "max_elevation_deg": 59.35,
        "visible_passes_count": 1,
        "avg_pass_duration_minutes": 36.0,
        "signal_strength_estimate_dbm": -58.81,
        "best_elevation_time": "2025-08-16T13:42:31.110522+00:00"
      },
      "leo_total_score": 82.22,
      "leo_visible_time_minutes": 36.0
    },
    {
      "norad_id": 45156,
      "name": "ONEWEB-45156",
      "elevation_deg": 57.05,
      "azimuth_deg": 180.0,
      "distance_km": 7000.0,
      "line1": "1 44713U 19074A   25227.50000000  .00001234  00000-0  12345-3 0  9990",
      "line2": "2 44713  87.9000 123.4567 0001234  12.3456 347.6543 13.20000000123456",
      "ecef_x_km": null,
      "ecef_y_km": null,
      "ecef_z_km": null,
      "constellation": "ONEWEB",
      "leo_visibility_analysis": {
        "total_visible_time_minutes": 35.5,
        "max_elevation_deg": 57.05,
        "visible_passes_count": 1,
        "avg_pass_duration_minutes": 35.5,
        "signal_strength_estimate_dbm": -58.95,
        "best_elevation_time": "2025-08-16T13:52:31.110522+00:00"
      },
      "leo_total_score": 81.51,
      "leo_visible_time_minutes": 35.5
    },
    {
      "norad_id": 45154,
      "name": "ONEWEB-45154",
      "elevation_deg": 55.71,
      "azimuth_deg": 180.0,
      "distance_km": 7000.0,
      "line1": "1 44713U 19074A   25227.50000000  .00001234  00000-0  12345-3 0  9990",
      "line2": "2 44713  87.9000 123.4567 0001234  12.3456 347.6543 13.20000000123456",
      "ecef_x_km": null,
      "ecef_y_km": null,
      "ecef_z_km": null,
      "constellation": "ONEWEB",
      "leo_visibility_analysis": {
        "total_visible_time_minutes": 35.5,
        "max_elevation_deg": 55.71,
        "visible_passes_count": 1,
        "avg_pass_duration_minutes": 35.5,
        "signal_strength_estimate_dbm": -59.19,
        "best_elevation_time": "2025-08-16T13:59:31.110522+00:00"
      },
      "leo_total_score": 81.29,
      "leo_visible_time_minutes": 35.5
    },
    {
      "norad_id": 45429,
      "name": "ONEWEB-45429",
      "elevation_deg": 45.61,
      "azimuth_deg": 180.0,
      "distance_km": 7000.0,
      "line1": "1 44713U 19074A   25227.50000000  .00001234  00000-0  12345-3 0  9990",
      "line2": "2 44713  87.9000 123.4567 0001234  12.3456 347.6543 13.20000000123456",
      "ecef_x_km": null,
      "ecef_y_km": null,
      "ecef_z_km": null,
      "constellation": "ONEWEB",
      "leo_visibility_analysis": {
        "total_visible_time_minutes": 35.0,
        "max_elevation_deg": 45.61,
        "visible_passes_count": 1,
        "avg_pass_duration_minutes": 35.0,
        "signal_strength_estimate_dbm": -60.86,
        "best_elevation_time": "2025-08-16T14:19:31.110522+00:00"
      },
      "leo_total_score": 79.27,
      "leo_visible_time_minutes": 35.0
    },
    {
      "norad_id": 45435,
      "name": "ONEWEB-45435",
      "elevation_deg": 47.92,
      "azimuth_deg": 180.0,
      "distance_km": 7000.0,
      "line1": "1 44713U 19074A   25227.50000000  .00001234  00000-0  12345-3 0  9990",
      "line2": "2 44713  87.9000 123.4567 0001234  12.3456 347.6543 13.20000000123456",
      "ecef_x_km": null,
      "ecef_y_km": null,
      "ecef_z_km": null,
      "constellation": "ONEWEB",
      "leo_visibility_analysis": {
        "total_visible_time_minutes": 35.0,
        "max_elevation_deg": 47.92,
        "visible_passes_count": 1,
        "avg_pass_duration_minutes": 35.0,
        "signal_strength_estimate_dbm": -60.48,
        "best_elevation_time": "2025-08-16T13:54:01.110522+00:00"
      },
      "leo_total_score": 79.65,
      "leo_visible_time_minutes": 35.0
    },
    {
      "norad_id": 45424,
      "name": "ONEWEB-45424",
      "elevation_deg": 45.98,
      "azimuth_deg": 180.0,
      "distance_km": 7000.0,
      "line1": "1 44713U 19074A   25227.50000000  .00001234  00000-0  12345-3 0  9990",
      "line2": "2 44713  87.9000 123.4567 0001234  12.3456 347.6543 13.20000000123456",
      "ecef_x_km": null,
      "ecef_y_km": null,
      "ecef_z_km": null,
      "constellation": "ONEWEB",
      "leo_visibility_analysis": {
        "total_visible_time_minutes": 35.0,
        "max_elevation_deg": 45.98,
        "visible_passes_count": 1,
        "avg_pass_duration_minutes": 35.0,
        "signal_strength_estimate_dbm": -60.81,
        "best_elevation_time": "2025-08-16T14:15:01.110522+00:00"
      },
      "leo_total_score": 79.33,
      "leo_visible_time_minutes": 35.0
    },
    {
      "norad_id": 45147,
      "name": "ONEWEB-45147",
      "elevation_deg": 62.39,
      "azimuth_deg": 180.0,
      "distance_km": 7000.0,
      "line1": "1 44713U 19074A   25227.50000000  .00001234  00000-0  12345-3 0  9990",
      "line2": "2 44713  87.9000 123.4567 0001234  12.3456 347.6543 13.20000000123456",
      "ecef_x_km": null,
      "ecef_y_km": null,
      "ecef_z_km": null,
      "constellation": "ONEWEB",
      "leo_visibility_analysis": {
        "total_visible_time_minutes": 34.0,
        "max_elevation_deg": 62.39,
        "visible_passes_count": 1,
        "avg_pass_duration_minutes": 34.0,
        "signal_strength_estimate_dbm": -57.88,
        "best_elevation_time": "2025-08-16T13:31:01.110522+00:00"
      },
      "leo_total_score": 81.4,
      "leo_visible_time_minutes": 34.0
    },
    {
      "norad_id": 45431,
      "name": "ONEWEB-45431",
      "elevation_deg": 51.25,
      "azimuth_deg": 180.0,
      "distance_km": 7000.0,
      "line1": "1 44713U 19074A   25227.50000000  .00001234  00000-0  12345-3 0  9990",
      "line2": "2 44713  87.9000 123.4567 0001234  12.3456 347.6543 13.20000000123456",
      "ecef_x_km": null,
      "ecef_y_km": null,
      "ecef_z_km": null,
      "constellation": "ONEWEB",
      "leo_visibility_analysis": {
        "total_visible_time_minutes": 31.5,
        "max_elevation_deg": 51.25,
        "visible_passes_count": 1,
        "avg_pass_duration_minutes": 31.5,
        "signal_strength_estimate_dbm": -58.86,
        "best_elevation_time": "2025-08-16T13:26:01.110522+00:00"
      },
      "leo_total_score": 77.87,
      "leo_visible_time_minutes": 31.5
    },
    {
      "norad_id": 45160,
      "name": "ONEWEB-45160",
      "elevation_deg": 55.5,
      "azimuth_deg": 180.0,
      "distance_km": 7000.0,
      "line1": "1 44713U 19074A   25227.50000000  .00001234  00000-0  12345-3 0  9990",
      "line2": "2 44713  87.9000 123.4567 0001234  12.3456 347.6543 13.20000000123456",
      "ecef_x_km": null,
      "ecef_y_km": null,
      "ecef_z_km": null,
      "constellation": "ONEWEB",
      "leo_visibility_analysis": {
        "total_visible_time_minutes": 36.0,
        "max_elevation_deg": 55.5,
        "visible_passes_count": 1,
        "avg_pass_duration_minutes": 36.0,
        "signal_strength_estimate_dbm": -59.22,
        "best_elevation_time": "2025-08-16T14:00:31.110522+00:00"
      },
      "leo_total_score": 81.58,
      "leo_visible_time_minutes": 36.0
    },
    {
      "norad_id": 45151,
      "name": "ONEWEB-45151",
      "elevation_deg": 44.23,
      "azimuth_deg": 180.0,
      "distance_km": 7000.0,
      "line1": "1 44713U 19074A   25227.50000000  .00001234  00000-0  12345-3 0  9990",
      "line2": "2 44713  87.9000 123.4567 0001234  12.3456 347.6543 13.20000000123456",
      "ecef_x_km": null,
      "ecef_y_km": null,
      "ecef_z_km": null,
      "constellation": "ONEWEB",
      "leo_visibility_analysis": {
        "total_visible_time_minutes": 28.5,
        "max_elevation_deg": 44.23,
        "visible_passes_count": 1,
        "avg_pass_duration_minutes": 28.5,
        "signal_strength_estimate_dbm": -61.67,
        "best_elevation_time": "2025-08-16T14:38:31.110522+00:00"
      },
      "leo_total_score": 74.7,
      "leo_visible_time_minutes": 28.5
    },
    {
      "norad_id": 45153,
      "name": "ONEWEB-45153",
      "elevation_deg": 56.4,
      "azimuth_deg": 180.0,
      "distance_km": 7000.0,
      "line1": "1 44713U 19074A   25227.50000000  .00001234  00000-0  12345-3 0  9990",
      "line2": "2 44713  87.9000 123.4567 0001234  12.3456 347.6543 13.20000000123456",
      "ecef_x_km": null,
      "ecef_y_km": null,
      "ecef_z_km": null,
      "constellation": "ONEWEB",
      "leo_visibility_analysis": {
        "total_visible_time_minutes": 35.5,
        "max_elevation_deg": 56.4,
        "visible_passes_count": 1,
        "avg_pass_duration_minutes": 35.5,
        "signal_strength_estimate_dbm": -59.06,
        "best_elevation_time": "2025-08-16T13:56:01.110522+00:00"
      },
      "leo_total_score": 81.4,
      "leo_visible_time_minutes": 35.5
    },
    {
      "norad_id": 45426,
      "name": "ONEWEB-45426",
      "elevation_deg": 50.17,
      "azimuth_deg": 180.0,
      "distance_km": 7000.0,
      "line1": "1 44713U 19074A   25227.50000000  .00001234  00000-0  12345-3 0  9990",
      "line2": "2 44713  87.9000 123.4567 0001234  12.3456 347.6543 13.20000000123456",
      "ecef_x_km": null,
      "ecef_y_km": null,
      "ecef_z_km": null,
      "constellation": "ONEWEB",
      "leo_visibility_analysis": {
        "total_visible_time_minutes": 35.0,
        "max_elevation_deg": 50.17,
        "visible_passes_count": 1,
        "avg_pass_duration_minutes": 35.0,
        "signal_strength_estimate_dbm": -60.04,
        "best_elevation_time": "2025-08-16T13:34:01.110522+00:00"
      },
      "leo_total_score": 80.03,
      "leo_visible_time_minutes": 35.0
    },
    {
      "norad_id": 44060,
      "name": "ONEWEB-44060",
      "elevation_deg": 54.23,
      "azimuth_deg": 180.0,
      "distance_km": 7000.0,
      "line1": "1 44713U 19074A   25227.50000000  .00001234  00000-0  12345-3 0  9990",
      "line2": "2 44713  87.9000 123.4567 0001234  12.3456 347.6543 13.20000000123456",
      "ecef_x_km": null,
      "ecef_y_km": null,
      "ecef_z_km": null,
      "constellation": "ONEWEB",
      "leo_visibility_analysis": {
        "total_visible_time_minutes": 35.5,
        "max_elevation_deg": 54.23,
        "visible_passes_count": 1,
        "avg_pass_duration_minutes": 35.5,
        "signal_strength_estimate_dbm": -59.34,
        "best_elevation_time": "2025-08-16T14:08:31.110522+00:00"
      },
      "leo_total_score": 81.04,
      "leo_visible_time_minutes": 35.5
    },
    {
      "norad_id": 45138,
      "name": "ONEWEB-45138",
      "elevation_deg": 58.03,
      "azimuth_deg": 180.0,
      "distance_km": 7000.0,
      "line1": "1 44713U 19074A   25227.50000000  .00001234  00000-0  12345-3 0  9990",
      "line2": "2 44713  87.9000 123.4567 0001234  12.3456 347.6543 13.20000000123456",
      "ecef_x_km": null,
      "ecef_y_km": null,
      "ecef_z_km": null,
      "constellation": "ONEWEB",
      "leo_visibility_analysis": {
        "total_visible_time_minutes": 36.0,
        "max_elevation_deg": 58.03,
        "visible_passes_count": 1,
        "avg_pass_duration_minutes": 36.0,
        "signal_strength_estimate_dbm": -58.86,
        "best_elevation_time": "2025-08-16T13:48:01.110522+00:00"
      },
      "leo_total_score": 82.0,
      "leo_visible_time_minutes": 36.0
    },
    {
      "norad_id": 45137,
      "name": "ONEWEB-45137",
      "elevation_deg": 64.45,
      "azimuth_deg": 180.0,
      "distance_km": 7000.0,
      "line1": "1 44713U 19074A   25227.50000000  .00001234  00000-0  12345-3 0  9990",
      "line2": "2 44713  87.9000 123.4567 0001234  12.3456 347.6543 13.20000000123456",
      "ecef_x_km": null,
      "ecef_y_km": null,
      "ecef_z_km": null,
      "constellation": "ONEWEB",
      "leo_visibility_analysis": {
        "total_visible_time_minutes": 27.0,
        "max_elevation_deg": 64.45,
        "visible_passes_count": 1,
        "avg_pass_duration_minutes": 27.0,
        "signal_strength_estimate_dbm": -55.49,
        "best_elevation_time": "2025-08-16T13:24:31.110522+00:00"
      },
      "leo_total_score": 77.08,
      "leo_visible_time_minutes": 27.0
    },
    {
      "norad_id": 45133,
      "name": "ONEWEB-45133",
      "elevation_deg": 63.73,
      "azimuth_deg": 180.0,
      "distance_km": 7000.0,
      "line1": "1 44713U 19074A   25227.50000000  .00001234  00000-0  12345-3 0  9990",
      "line2": "2 44713  87.9000 123.4567 0001234  12.3456 347.6543 13.20000000123456",
      "ecef_x_km": null,
      "ecef_y_km": null,
      "ecef_z_km": null,
      "constellation": "ONEWEB",
      "leo_visibility_analysis": {
        "total_visible_time_minutes": 29.5,
        "max_elevation_deg": 63.73,
        "visible_passes_count": 1,
        "avg_pass_duration_minutes": 29.5,
        "signal_strength_estimate_dbm": -56.3,
        "best_elevation_time": "2025-08-16T13:26:31.110522+00:00"
      },
      "leo_total_score": 78.62,
      "leo_visible_time_minutes": 29.5
    },
    {
      "norad_id": 45159,
      "name": "ONEWEB-45159",
      "elevation_deg": 57.54,
      "azimuth_deg": 180.0,
      "distance_km": 7000.0,
      "line1": "1 44713U 19074A   25227.50000000  .00001234  00000-0  12345-3 0  9990",
      "line2": "2 44713  87.9000 123.4567 0001234  12.3456 347.6543 13.20000000123456",
      "ecef_x_km": null,
      "ecef_y_km": null,
      "ecef_z_km": null,
      "constellation": "ONEWEB",
      "leo_visibility_analysis": {
        "total_visible_time_minutes": 35.5,
        "max_elevation_deg": 57.54,
        "visible_passes_count": 1,
        "avg_pass_duration_minutes": 35.5,
        "signal_strength_estimate_dbm": -58.94,
        "best_elevation_time": "2025-08-16T13:50:31.110522+00:00"
      },
      "leo_total_score": 81.59,
      "leo_visible_time_minutes": 35.5
    },
    {
      "norad_id": 45428,
      "name": "ONEWEB-45428",
      "elevation_deg": 43.78,
      "azimuth_deg": 180.0,
      "distance_km": 7000.0,
      "line1": "1 44713U 19074A   25227.50000000  .00001234  00000-0  12345-3 0  9990",
      "line2": "2 44713  87.9000 123.4567 0001234  12.3456 347.6543 13.20000000123456",
      "ecef_x_km": null,
      "ecef_y_km": null,
      "ecef_z_km": null,
      "constellation": "ONEWEB",
      "leo_visibility_analysis": {
        "total_visible_time_minutes": 26.0,
        "max_elevation_deg": 43.78,
        "visible_passes_count": 2,
        "avg_pass_duration_minutes": 13.0,
        "signal_strength_estimate_dbm": -61.21,
        "best_elevation_time": "2025-08-16T14:45:01.110522+00:00"
      },
      "leo_total_score": 72.96,
      "leo_visible_time_minutes": 26.0
    },
    {
      "norad_id": 45150,
      "name": "ONEWEB-45150",
      "elevation_deg": 53.49,
      "azimuth_deg": 180.0,
      "distance_km": 7000.0,
      "line1": "1 44713U 19074A   25227.50000000  .00001234  00000-0  12345-3 0  9990",
      "line2": "2 44713  87.9000 123.4567 0001234  12.3456 347.6543 13.20000000123456",
      "ecef_x_km": null,
      "ecef_y_km": null,
      "ecef_z_km": null,
      "constellation": "ONEWEB",
      "leo_visibility_analysis": {
        "total_visible_time_minutes": 35.5,
        "max_elevation_deg": 53.49,
        "visible_passes_count": 1,
        "avg_pass_duration_minutes": 35.5,
        "signal_strength_estimate_dbm": -59.53,
        "best_elevation_time": "2025-08-16T14:11:31.110522+00:00"
      },
      "leo_total_score": 80.91,
      "leo_visible_time_minutes": 35.5
    },
    {
      "norad_id": 44061,
      "name": "ONEWEB-44061",
      "elevation_deg": 55.25,
      "azimuth_deg": 180.0,
      "distance_km": 7000.0,
      "line1": "1 44713U 19074A   25227.50000000  .00001234  00000-0  12345-3 0  9990",
      "line2": "2 44713  87.9000 123.4567 0001234  12.3456 347.6543 13.20000000123456",
      "ecef_x_km": null,
      "ecef_y_km": null,
      "ecef_z_km": null,
      "constellation": "ONEWEB",
      "leo_visibility_analysis": {
        "total_visible_time_minutes": 35.0,
        "max_elevation_deg": 55.25,
        "visible_passes_count": 1,
        "avg_pass_duration_minutes": 35.0,
        "signal_strength_estimate_dbm": -59.2,
        "best_elevation_time": "2025-08-16T14:14:01.110522+00:00"
      },
      "leo_total_score": 80.88,
      "leo_visible_time_minutes": 35.0
    },
    {
      "norad_id": 45427,
      "name": "ONEWEB-45427",
      "elevation_deg": 47.23,
      "azimuth_deg": 180.0,
      "distance_km": 7000.0,
      "line1": "1 44713U 19074A   25227.50000000  .00001234  00000-0  12345-3 0  9990",
      "line2": "2 44713  87.9000 123.4567 0001234  12.3456 347.6543 13.20000000123456",
      "ecef_x_km": null,
      "ecef_y_km": null,
      "ecef_z_km": null,
      "constellation": "ONEWEB",
      "leo_visibility_analysis": {
        "total_visible_time_minutes": 35.0,
        "max_elevation_deg": 47.23,
        "visible_passes_count": 1,
        "avg_pass_duration_minutes": 35.0,
        "signal_strength_estimate_dbm": -60.55,
        "best_elevation_time": "2025-08-16T14:01:01.110522+00:00"
      },
      "leo_total_score": 79.54,
      "leo_visible_time_minutes": 35.0
    },
    {
      "norad_id": 45140,
      "name": "ONEWEB-45140",
      "elevation_deg": 50.48,
      "azimuth_deg": 180.0,
      "distance_km": 7000.0,
      "line1": "1 44713U 19074A   25227.50000000  .00001234  00000-0  12345-3 0  9990",
      "line2": "2 44713  87.9000 123.4567 0001234  12.3456 347.6543 13.20000000123456",
      "ecef_x_km": null,
      "ecef_y_km": null,
      "ecef_z_km": null,
      "constellation": "ONEWEB",
      "leo_visibility_analysis": {
        "total_visible_time_minutes": 35.5,
        "max_elevation_deg": 50.48,
        "visible_passes_count": 1,
        "avg_pass_duration_minutes": 35.5,
        "signal_strength_estimate_dbm": -59.96,
        "best_elevation_time": "2025-08-16T13:31:31.110522+00:00"
      },
      "leo_total_score": 80.41,
      "leo_visible_time_minutes": 35.5
    },
    {
      "norad_id": 45146,
      "name": "ONEWEB-45146",
      "elevation_deg": 59.92,
      "azimuth_deg": 180.0,
      "distance_km": 7000.0,
      "line1": "1 44713U 19074A   25227.50000000  .00001234  00000-0  12345-3 0  9990",
      "line2": "2 44713  87.9000 123.4567 0001234  12.3456 347.6543 13.20000000123456",
      "ecef_x_km": null,
      "ecef_y_km": null,
      "ecef_z_km": null,
      "constellation": "ONEWEB",
      "leo_visibility_analysis": {
        "total_visible_time_minutes": 36.0,
        "max_elevation_deg": 59.92,
        "visible_passes_count": 1,
        "avg_pass_duration_minutes": 36.0,
        "signal_strength_estimate_dbm": -58.71,
        "best_elevation_time": "2025-08-16T13:40:01.110522+00:00"
      },
      "leo_total_score": 82.32,
      "leo_visible_time_minutes": 36.0
    },
    {
      "norad_id": 45157,
      "name": "ONEWEB-45157",
      "elevation_deg": 63.11,
      "azimuth_deg": 180.0,
      "distance_km": 7000.0,
      "line1": "1 44713U 19074A   25227.50000000  .00001234  00000-0  12345-3 0  9990",
      "line2": "2 44713  87.9000 123.4567 0001234  12.3456 347.6543 13.20000000123456",
      "ecef_x_km": null,
      "ecef_y_km": null,
      "ecef_z_km": null,
      "constellation": "ONEWEB",
      "leo_visibility_analysis": {
        "total_visible_time_minutes": 31.5,
        "max_elevation_deg": 63.11,
        "visible_passes_count": 1,
        "avg_pass_duration_minutes": 31.5,
        "signal_strength_estimate_dbm": -57.12,
        "best_elevation_time": "2025-08-16T13:29:01.110522+00:00"
      },
      "leo_total_score": 79.85,
      "leo_visible_time_minutes": 31.5
    },
    {
      "norad_id": 45143,
      "name": "ONEWEB-45143",
      "elevation_deg": 52.62,
      "azimuth_deg": 180.0,
      "distance_km": 7000.0,
      "line1": "1 44713U 19074A   25227.50000000  .00001234  00000-0  12345-3 0  9990",
      "line2": "2 44713  87.9000 123.4567 0001234  12.3456 347.6543 13.20000000123456",
      "ecef_x_km": null,
      "ecef_y_km": null,
      "ecef_z_km": null,
      "constellation": "ONEWEB",
      "leo_visibility_analysis": {
        "total_visible_time_minutes": 35.5,
        "max_elevation_deg": 52.62,
        "visible_passes_count": 1,
        "avg_pass_duration_minutes": 35.5,
        "signal_strength_estimate_dbm": -59.64,
        "best_elevation_time": "2025-08-16T14:17:31.110522+00:00"
      },
      "leo_total_score": 80.77,
      "leo_visible_time_minutes": 35.5
    },
    {
      "norad_id": 45162,
      "name": "ONEWEB-45162",
      "elevation_deg": 60.54,
      "azimuth_deg": 180.0,
      "distance_km": 7000.0,
      "line1": "1 44713U 19074A   25227.50000000  .00001234  00000-0  12345-3 0  9990",
      "line2": "2 44713  87.9000 123.4567 0001234  12.3456 347.6543 13.20000000123456",
      "ecef_x_km": null,
      "ecef_y_km": null,
      "ecef_z_km": null,
      "constellation": "ONEWEB",
      "leo_visibility_analysis": {
        "total_visible_time_minutes": 35.5,
        "max_elevation_deg": 60.54,
        "visible_passes_count": 1,
        "avg_pass_duration_minutes": 35.5,
        "signal_strength_estimate_dbm": -58.56,
        "best_elevation_time": "2025-08-16T13:38:01.110522+00:00"
      },
      "leo_total_score": 82.09,
      "leo_visible_time_minutes": 35.5
    },
    {
      "norad_id": 45142,
      "name": "ONEWEB-45142",
      "elevation_deg": 61.13,
      "azimuth_deg": 180.0,
      "distance_km": 7000.0,
      "line1": "1 44713U 19074A   25227.50000000  .00001234  00000-0  12345-3 0  9990",
      "line2": "2 44713  87.9000 123.4567 0001234  12.3456 347.6543 13.20000000123456",
      "ecef_x_km": null,
      "ecef_y_km": null,
      "ecef_z_km": null,
      "constellation": "ONEWEB",
      "leo_visibility_analysis": {
        "total_visible_time_minutes": 35.5,
        "max_elevation_deg": 61.13,
        "visible_passes_count": 1,
        "avg_pass_duration_minutes": 35.5,
        "signal_strength_estimate_dbm": -58.54,
        "best_elevation_time": "2025-08-16T13:35:31.110522+00:00"
      },
      "leo_total_score": 82.19,
      "leo_visible_time_minutes": 35.5
    },
    {
      "norad_id": 45139,
      "name": "ONEWEB-45139",
      "elevation_deg": 44.72,
      "azimuth_deg": 180.0,
      "distance_km": 7000.0,
      "line1": "1 44713U 19074A   25227.50000000  .00001234  00000-0  12345-3 0  9990",
      "line2": "2 44713  87.9000 123.4567 0001234  12.3456 347.6543 13.20000000123456",
      "ecef_x_km": null,
      "ecef_y_km": null,
      "ecef_z_km": null,
      "constellation": "ONEWEB",
      "leo_visibility_analysis": {
        "total_visible_time_minutes": 35.0,
        "max_elevation_deg": 44.72,
        "visible_passes_count": 1,
        "avg_pass_duration_minutes": 35.0,
        "signal_strength_estimate_dbm": -61.07,
        "best_elevation_time": "2025-08-16T14:31:31.110522+00:00"
      },
      "leo_total_score": 79.12,
      "leo_visible_time_minutes": 35.0
    },
    {
      "norad_id": 45164,
      "name": "ONEWEB-45164",
      "elevation_deg": 58.58,
      "azimuth_deg": 180.0,
      "distance_km": 7000.0,
      "line1": "1 44713U 19074A   25227.50000000  .00001234  00000-0  12345-3 0  9990",
      "line2": "2 44713  87.9000 123.4567 0001234  12.3456 347.6543 13.20000000123456",
      "ecef_x_km": null,
      "ecef_y_km": null,
      "ecef_z_km": null,
      "constellation": "ONEWEB",
      "leo_visibility_analysis": {
        "total_visible_time_minutes": 36.0,
        "max_elevation_deg": 58.58,
        "visible_passes_count": 1,
        "avg_pass_duration_minutes": 36.0,
        "signal_strength_estimate_dbm": -58.83,
        "best_elevation_time": "2025-08-16T13:46:01.110522+00:00"
      },
      "leo_total_score": 82.1,
      "leo_visible_time_minutes": 36.0
    },
    {
      "norad_id": 45163,
      "name": "ONEWEB-45163",
      "elevation_deg": 53.32,
      "azimuth_deg": 180.0,
      "distance_km": 7000.0,
      "line1": "1 44713U 19074A   25227.50000000  .00001234  00000-0  12345-3 0  9990",
      "line2": "2 44713  87.9000 123.4567 0001234  12.3456 347.6543 13.20000000123456",
      "ecef_x_km": null,
      "ecef_y_km": null,
      "ecef_z_km": null,
      "constellation": "ONEWEB",
      "leo_visibility_analysis": {
        "total_visible_time_minutes": 36.0,
        "max_elevation_deg": 53.32,
        "visible_passes_count": 1,
        "avg_pass_duration_minutes": 36.0,
        "signal_strength_estimate_dbm": -59.56,
        "best_elevation_time": "2025-08-16T14:13:01.110522+00:00"
      },
      "leo_total_score": 81.22,
      "leo_visible_time_minutes": 36.0
    },
    {
      "norad_id": 45158,
      "name": "ONEWEB-45158",
      "elevation_deg": 52.77,
      "azimuth_deg": 180.0,
      "distance_km": 7000.0,
      "line1": "1 44713U 19074A   25227.50000000  .00001234  00000-0  12345-3 0  9990",
      "line2": "2 44713  87.9000 123.4567 0001234  12.3456 347.6543 13.20000000123456",
      "ecef_x_km": null,
      "ecef_y_km": null,
      "ecef_z_km": null,
      "constellation": "ONEWEB",
      "leo_visibility_analysis": {
        "total_visible_time_minutes": 35.5,
        "max_elevation_deg": 52.77,
        "visible_passes_count": 1,
        "avg_pass_duration_minutes": 35.5,
        "signal_strength_estimate_dbm": -59.55,
        "best_elevation_time": "2025-08-16T14:16:01.110522+00:00"
      },
      "leo_total_score": 80.79,
      "leo_visible_time_minutes": 35.5
    },
    {
      "norad_id": 45134,
      "name": "ONEWEB-45134",
      "elevation_deg": 58.33,
      "azimuth_deg": 180.0,
      "distance_km": 7000.0,
      "line1": "1 44713U 19074A   25227.50000000  .00001234  00000-0  12345-3 0  9990",
      "line2": "2 44713  87.9000 123.4567 0001234  12.3456 347.6543 13.20000000123456",
      "ecef_x_km": null,
      "ecef_y_km": null,
      "ecef_z_km": null,
      "constellation": "ONEWEB",
      "leo_visibility_analysis": {
        "total_visible_time_minutes": 35.5,
        "max_elevation_deg": 58.33,
        "visible_passes_count": 1,
        "avg_pass_duration_minutes": 35.5,
        "signal_strength_estimate_dbm": -58.82,
        "best_elevation_time": "2025-08-16T13:47:01.110522+00:00"
      },
      "leo_total_score": 81.72,
      "leo_visible_time_minutes": 35.5
    },
    {
      "norad_id": 44059,
      "name": "ONEWEB-44059",
      "elevation_deg": 86.11,
      "azimuth_deg": 180.0,
      "distance_km": 7000.0,
      "line1": "1 44713U 19074A   25227.50000000  .00001234  00000-0  12345-3 0  9990",
      "line2": "2 44713  87.9000 123.4567 0001234  12.3456 347.6543 13.20000000123456",
      "ecef_x_km": null,
      "ecef_y_km": null,
      "ecef_z_km": null,
      "constellation": "ONEWEB",
      "leo_visibility_analysis": {
        "total_visible_time_minutes": 36.5,
        "max_elevation_deg": 86.11,
        "visible_passes_count": 1,
        "avg_pass_duration_minutes": 36.5,
        "signal_strength_estimate_dbm": -57.11,
        "best_elevation_time": "2025-08-16T13:33:01.110522+00:00"
      },
      "leo_total_score": 87.02,
      "leo_visible_time_minutes": 36.5
    },
    {
      "norad_id": 44057,
      "name": "ONEWEB-44057",
      "elevation_deg": 72.33,
      "azimuth_deg": 180.0,
      "distance_km": 7000.0,
      "line1": "1 44713U 19074A   25227.50000000  .00001234  00000-0  12345-3 0  9990",
      "line2": "2 44713  87.9000 123.4567 0001234  12.3456 347.6543 13.20000000123456",
      "ecef_x_km": null,
      "ecef_y_km": null,
      "ecef_z_km": null,
      "constellation": "ONEWEB",
      "leo_visibility_analysis": {
        "total_visible_time_minutes": 36.0,
        "max_elevation_deg": 72.33,
        "visible_passes_count": 1,
        "avg_pass_duration_minutes": 36.0,
        "signal_strength_estimate_dbm": -57.62,
        "best_elevation_time": "2025-08-16T14:10:31.110522+00:00"
      },
      "leo_total_score": 84.39,
      "leo_visible_time_minutes": 36.0
    },
    {
      "norad_id": 45152,
      "name": "ONEWEB-45152",
      "elevation_deg": 55.07,
      "azimuth_deg": 180.0,
      "distance_km": 7000.0,
      "line1": "1 44713U 19074A   25227.50000000  .00001234  00000-0  12345-3 0  9990",
      "line2": "2 44713  87.9000 123.4567 0001234  12.3456 347.6543 13.20000000123456",
      "ecef_x_km": null,
      "ecef_y_km": null,
      "ecef_z_km": null,
      "constellation": "ONEWEB",
      "leo_visibility_analysis": {
        "total_visible_time_minutes": 35.5,
        "max_elevation_deg": 55.07,
        "visible_passes_count": 1,
        "avg_pass_duration_minutes": 35.5,
        "signal_strength_estimate_dbm": -59.29,
        "best_elevation_time": "2025-08-16T14:02:31.110522+00:00"
      },
      "leo_total_score": 81.18,
      "leo_visible_time_minutes": 35.5
    },
    {
      "norad_id": 44058,
      "name": "ONEWEB-44058",
      "elevation_deg": 53.26,
      "azimuth_deg": 180.0,
      "distance_km": 7000.0,
      "line1": "1 44713U 19074A   25227.50000000  .00001234  00000-0  12345-3 0  9990",
      "line2": "2 44713  87.9000 123.4567 0001234  12.3456 347.6543 13.20000000123456",
      "ecef_x_km": null,
      "ecef_y_km": null,
      "ecef_z_km": null,
      "constellation": "ONEWEB",
      "leo_visibility_analysis": {
        "total_visible_time_minutes": 26.5,
        "max_elevation_deg": 53.26,
        "visible_passes_count": 2,
        "avg_pass_duration_minutes": 13.25,
        "signal_strength_estimate_dbm": -60.73,
        "best_elevation_time": "2025-08-16T13:05:31.110522+00:00"
      },
      "leo_total_score": 74.88,
      "leo_visible_time_minutes": 26.5
    },
    {
      "norad_id": 45434,
      "name": "ONEWEB-45434",
      "elevation_deg": 46.59,
      "azimuth_deg": 180.0,
      "distance_km": 7000.0,
      "line1": "1 44713U 19074A   25227.50000000  .00001234  00000-0  12345-3 0  9990",
      "line2": "2 44713  87.9000 123.4567 0001234  12.3456 347.6543 13.20000000123456",
      "ecef_x_km": null,
      "ecef_y_km": null,
      "ecef_z_km": null,
      "constellation": "ONEWEB",
      "leo_visibility_analysis": {
        "total_visible_time_minutes": 35.0,
        "max_elevation_deg": 46.59,
        "visible_passes_count": 1,
        "avg_pass_duration_minutes": 35.0,
        "signal_strength_estimate_dbm": -60.62,
        "best_elevation_time": "2025-08-16T14:08:01.110522+00:00"
      },
      "leo_total_score": 79.43,
      "leo_visible_time_minutes": 35.0
    },
    {
      "norad_id": 45144,
      "name": "ONEWEB-45144",
      "elevation_deg": 54.83,
      "azimuth_deg": 180.0,
      "distance_km": 7000.0,
      "line1": "1 44713U 19074A   25227.50000000  .00001234  00000-0  12345-3 0  9990",
      "line2": "2 44713  87.9000 123.4567 0001234  12.3456 347.6543 13.20000000123456",
      "ecef_x_km": null,
      "ecef_y_km": null,
      "ecef_z_km": null,
      "constellation": "ONEWEB",
      "leo_visibility_analysis": {
        "total_visible_time_minutes": 36.0,
        "max_elevation_deg": 54.83,
        "visible_passes_count": 1,
        "avg_pass_duration_minutes": 36.0,
        "signal_strength_estimate_dbm": -59.33,
        "best_elevation_time": "2025-08-16T14:04:01.110522+00:00"
      },
      "leo_total_score": 81.47,
      "leo_visible_time_minutes": 36.0
    }
  ],
  "statistics": {
    "total_satellites": 100,
    "starlink_count": 50,
    "oneweb_count": 50,
    "avg_elevation": 44.263000000000005,
    "max_elevation": 86.11
  }
}